fimpef/BuildingFootprint/__init__.py
fimpef/BuildingFootprint/evaluationwithBF.py
fimpef/ContingencyMap/PWBs3.py
fimpef/ContingencyMap/__init__.py
fimpef/ContingencyMap/evaluationFIM.py
fimpef/ContingencyMap/methods.py
fimpef/ContingencyMap/metrics.py
fimpef/ContingencyMap/plotevaluationmetrics.py
fimpef/ContingencyMap/printcontingency.py
fimpef/__init__.py
fimpef-0.1.42.dist-info/LICENSE.txt
fimpef-0.1.42.dist-info/METADATA
fimpef-0.1.42.dist-info/WHEEL
fimpef-0.1.42.dist-info/RECORD
