Metadata-Version: 2.1
Name: fimpef
Version: 0.1.42
Summary: A Framework for Automatic Evaluation of Flood Inundation Mapping Predictions Evaluation
License: GPLv3
Author: Surface Dynamics Modeling Lab
Maintainer: Supath Dhital
Maintainer-email: sdhital@crimson.ua.edu
Requires-Python: >=3.10,<4.0
Classifier: License :: Other/Proprietary License
Classifier: Programming Language :: Python :: 3
Classifier: Programming Language :: Python :: 3.10
Classifier: Programming Language :: Python :: 3.11
Classifier: Programming Language :: Python :: 3.12
Classifier: Programming Language :: Python :: 3.13
Requires-Dist: boto3 (>=1.36.16,<2.0.0)
Requires-Dist: geopandas (>=1.0.1,<2.0.0)
Requires-Dist: kaleido (==0.2.1)
Requires-Dist: matplotlib (>=3.9.2,<4.0.0)
Requires-Dist: msfootprint (>=0.1.27,<0.2.0)
Requires-Dist: nbformat (>=5.10.4,<6.0.0)
Requires-Dist: notebook (>=7.3.2,<8.0.0)
Requires-Dist: numpy (<2)
Requires-Dist: pathlib (>=1.0.1,<2.0.0)
Requires-Dist: plotly (>=5.24.1,<6.0.0)
Requires-Dist: pyproj (>=3.7.0,<4.0.0)
Requires-Dist: pytest (>=8.3.3,<9.0.0)
Requires-Dist: rasterio (>=1.4.2,<2.0.0)
Requires-Dist: shapely (>=2.0.6,<3.0.0)
